{
  "e1": [
    {
      "expo": 1,
      "table": 1,
      "project": "Montivity"
    },
    {
      "expo": 1,
      "table": 2,
      "project": "SanaTree"
    },
    {
      "expo": 1,
      "table": 3,
      "project": "Rainbow 7 Siege"
    },
    {
      "expo": 1,
      "table": 4,
      "project": "Pokegatchi"
    },
    {
      "expo": 1,
      "table": 5,
      "project": "Kitchen Kalc"
    },
    {
      "expo": 1,
      "table": 6,
      "project": "MemShape"
    },
    {
      "expo": 1,
      "table": 7,
      "project": "3AM-Buddy (Should I send this text?)"
    },
    {
      "expo": 1,
      "table": 8,
      "project": "Zot Clicker"
    },
    {
      "expo": 1,
      "table": 9,
      "project": "WebMD 2.0"
    },
    {
      "expo": 1,
      "table": 10,
      "project": "Osu Replay Cheat Analyzer"
    },
    {
      "expo": 1,
      "table": 11,
      "project": "ZotReqs"
    },
    {
      "expo": 1,
      "table": 12,
      "project": "PCBuddy"
    },
    {
      "expo": 1,
      "table": 13,
      "project": "Find It - Real Time Document Search"
    },
    {
      "expo": 1,
      "table": 14,
      "project": "Lyrica"
    },
    {
      "expo": 1,
      "table": 15,
      "project": "SoundHub"
    },
    {
      "expo": 1,
      "table": 16,
      "project": "Groops"
    },
    {
      "expo": 1,
      "table": 17,
      "project": "MedGuys"
    },
    {
      "expo": 1,
      "table": 18,
      "project": "Greed of The Nine Winds"
    }
  ],
  "e2": [
    {
      "expo": 2,
      "table": 19,
      "project": "MyREG"
    },
    {
      "expo": 2,
      "table": 20,
      "project": "FoodSlider"
    },
    {
      "expo": 2,
      "table": 21,
      "project": "VeriPrint"
    },
    {
      "expo": 2,
      "table": 22,
      "project": "EDUrate - Youtube"
    },
    {
      "expo": 2,
      "table": 23,
      "project": "ACM@UCR Link"
    },
    {
      "expo": 2,
      "table": 24,
      "project": "HYP."
    },
    {
      "expo": 2,
      "table": 25,
      "project": "Super Smash Anglers"
    },
    {
      "expo": 2,
      "table": 26,
      "project": "HackUCI"
    },
    {
      "expo": 2,
      "table": 27,
      "project": "ChickInfinite"
    },
    {
      "expo": 2,
      "table": 28,
      "project": "instanurse"
    },
    {
      "expo": 2,
      "table": 29,
      "project": "datasponge"
    },
    {
      "expo": 2,
      "table": 30,
      "project": "HaleCoin"
    },
    {
      "expo": 2,
      "table": 31,
      "project": "Hardware Maze"
    },
    {
      "expo": 2,
      "table": 32,
      "project": "HealthWeb"
    },
    {
      "expo": 2,
      "table": 33,
      "project": "Earnings Tracker"
    },
    {
      "expo": 2,
      "table": 34,
      "project": "Pink"
    },
    {
      "expo": 2,
      "table": 35,
      "project": "Fed Up"
    }
  ],
  "e3": [
    {
      "expo": 3,
      "table": 36,
      "project": "Konnect"
    },
    {
      "expo": 3,
      "table": 37,
      "project": "MedChain"
    },
    {
      "expo": 3,
      "table": 38,
      "project": "UCI Course Dependency Graph"
    },
    {
      "expo": 3,
      "table": 39,
      "project": "LaundryRoom"
    },
    {
      "expo": 3,
      "table": 40,
      "project": "ChitChat.tech"
    },
    {
      "expo": 3,
      "table": 41,
      "project": "Rhythm Racket"
    },
    {
      "expo": 3,
      "table": 42,
      "project": "Nutrition AR"
    },
    {
      "expo": 3,
      "table": 43,
      "project": "tide pod bot"
    },
    {
      "expo": 3,
      "table": 44,
      "project": "personiYou"
    },
    {
      "expo": 3,
      "table": 45,
      "project": "QTime"
    },
    {
      "expo": 3,
      "table": 46,
      "project": "Pact"
    },
    {
      "expo": 3,
      "table": 47,
      "project": "newsflash"
    },
    {
      "expo": 3,
      "table": 48,
      "project": "TopDog"
    },
    {
      "expo": 3,
      "table": 49,
      "project": "Virtual Trainer"
    },
    {
      "expo": 3,
      "table": 50,
      "project": "Support Group Connect"
    },
    {
      "expo": 3,
      "table": 51,
      "project": "Main Menu"
    },
    {
      "expo": 3,
      "table": 52,
      "project": "Woof"
    },
    {
      "expo": 3,
      "table": 53,
      "project": "test"
    },
    {
      "expo": 3,
      "table": 54,
      "project": "Tend Your Greens"
    },
    {
      "expo": 3,
      "table": 55,
      "project": "CharityBet"
    },
    {
      "expo": 3,
      "table": 56,
      "project": "healthie"
    },
    {
      "expo": 3,
      "table": 57,
      "project": "QuotEm"
    },
    {
      "expo": 3,
      "table": 58,
      "project": "DEFCON"
    },
    {
      "expo": 3,
      "table": 59,
      "project": "Broke"
    },
    {
      "expo": 3,
      "table": 60,
      "project": "ARan-Concept"
    },
    {
      "expo": 3,
      "table": 61,
      "project": "Picme"
    },
    {
      "expo": 3,
      "table": 62,
      "project": "Math Explorer"
    },
    {
      "expo": 3,
      "table": 63,
      "project": "All the Feels"
    },
    {
      "expo": 3,
      "table": 64,
      "project": "MyGroceryPal"
    },
    {
      "expo": 3,
      "table": 65,
      "project": "Muscle Guru"
    },
    {
      "expo": 3,
      "table": 66,
      "project": "Exciting Title"
    },
    {
      "expo": 3,
      "table": 67,
      "project": "Color Shot"
    },
    {
      "expo": 3,
      "table": 68,
      "project": "ai_syte"
    },
    {
      "expo": 3,
      "table": 69,
      "project": "Sign-In"
    },
    {
      "expo": 3,
      "table": 70,
      "project": "EasyRoad"
    },
    {
      "expo": 3,
      "table": 71,
      "project": "Best Before"
    },
    {
      "expo": 3,
      "table": 72,
      "project": "Valerian"
    },
    {
      "expo": 3,
      "table": 73,
      "project": "CheckUp"
    },
    {
      "expo": 3,
      "table": 74,
      "project": "Today and Tomorrow"
    }
  ]
}