{
    "friday": [
        {
            "name": "Walk-In Line Starts",
            "time": "6:00-7:00pm",
            "location": "Ballroom Lobby"
        },
        {
            "name": "Check-In",
            "time": "7:00-9:00pm",
            "location": "Ballroom Lobby"
        },
        {
            "name": "Dinner",
            "time": "7:00-9:00pm",
            "location": "Pacific Ballroom Patio"
        },
        {
            "name": "Opening Ceremony",
            "time": "9:00-10:00pm",
            "location": "Pacific Ballroom"
        },
        {
            "name": "Team Formation",
            "time": "10:00-10:30pm",
            "location": "Ballroom Lobby"
        },
        {
            "name": "How to Hack and Heroku Workshop",
            "time": "10:30pm-12:00am",
            "location": "Moss Cove"
        },
        {
            "name": "Rap Battle",
            "time": "12:00-1:00am",
            "location": "Pacific Ballroom"
        }
    ],
    "saturday": [
        {
            "name": "Breakfast",
            "time": "7.30-8.30am",
            "location": "Pacific Ballroom"
        },
        {
            "name": "Meditation",
            "time": "9:00-10:00am",
            "location": "Aldrich Park"
        },
        {
            "name": "Shirts Distribution",
            "time": "10:00am",
            "location": "Moss Cove"
        },
        {
            "name": "Paper Airplane Activity",
            "time": "11:00am",
            "location": "Ballroom Lobby"
        },
        {
            "name": "Lunch",
            "time": "12:30pm",
            "location": "Pacific Ballroom Patio"
        },
        {
            "name": "Raffles",
            "time": "2:00pm",
            "location": "Pacific Ballroom"
        },
        {
            "name": "Smash Bros",
            "time": "3:00pm",
            "location": "Moss Cove"
        },
        {
            "name": "Octocat Drawing Contest",
            "time": "4:00pm",
            "location": "Pacific Ballroom"
        },
        {
            "name": "Dinner",
            "time": "7:00pm",
            "location": "Pacific Ballroom Patio"
        },
        {
            "name": "Cupstacking Challenge",
            "time": "9:00pm",
            "location": "Pacific Ballroom"
        }
    ],
    "sunday": [
        {
            "name": "Stroll In Aldrich Park",
            "time": "6:00am",
            "location": "Aldrich Park"
        },
        {
            "name": "Breakfast",
            "time": "7:00am",
            "location": "Pacific Ballroom"
        },
        {
            "name": "Hacking Ends",
            "time": "10:00am",
            "location": "Pacific Ballroom"
        },
        {
            "name": "Prep for Expo",
            "time": "10:00-11:00am",
            "location": "Pacific Ballroom, Woods Cove & Moss Cove"
        },
        {
            "name": "Lunch",
            "time": "11:00am",
            "location": "Pacific Ballroom Patio"
        },
        {
            "name": "Expo",
            "time": "12:00-2:30pm",
            "location": "Moss Cove & Woods Cove"
        },
        {
            "name": "Closing Ceremony",
            "time": "2:30-3:30pm",
            "location": "Pacific Ballroom"
        }
    ]
}